[
  {
    "lead_id": "candidate_1769021459@test.com",
    "timestamp": "2026-01-21 21:50:59",
    "email": "candidate_1769021459@test.com",
    "first_name": "Mary",
    "middle_name": null,
    "last_name": "Otieno",
    "phone": "254700000000",
    "source": "Web",
    "current_profession": "Nurse",
    "experience_years": "3-4+ Years",
    "has_business_exp": "Yes",
    "certifications": null,
    "financial_readiness_input": "I need a loan",
    "location_county_input": "Thika",
    "location_status_input": "No",
    "stage": "POTENTIAL_FIT",
    "fit_score": 0.19,
    "fit_classification": "Good Fit",
    "financial_readiness": "\ud83d\udfe0 Nurture",
    "location_readiness": "\ud83d\udd34 Not Ready",
    "draft_message": "TO: candidate_1769021459@test.com\nCHANNEL: WhatsApp (+254700000000)\n\nHabari Mary! \ud83d\udc4b\n\nWe think you could be a great fit for Curafa given your background as a Nurse.\n\nWe are expanding in Thika and would like to discuss next steps.\n\n(Note: We saw you mentioned needing financing. We have banking partners who assist Curafa franchisees with working capital\u2014we can discuss this on the call.)\n\nAre you free next Tuesday for a 15-min intro call?",
    "next_step_due_date": "2026-01-28",
    "notes": null,
    "last_contact_date": null,
    "last_contact_channel": null
  },
  {
    "lead_id": "candidate_1769021533@test.com",
    "timestamp": "2026-01-21 21:52:13",
    "email": "candidate_1769021533@test.com",
    "first_name": "Juma",
    "middle_name": null,
    "last_name": "Ali",
    "phone": "254700000000",
    "source": "Web",
    "current_profession": "Nurse",
    "experience_years": "1-2 Years",
    "has_business_exp": "Yes",
    "certifications": null,
    "financial_readiness_input": "I need a loan",
    "location_county_input": "Kibera",
    "location_status_input": "No",
    "stage": "POTENTIAL_FIT",
    "fit_score": 0.17,
    "fit_classification": "Fair/Conditional Fit",
    "financial_readiness": "\ud83d\udfe0 Nurture",
    "location_readiness": "\ud83d\udd34 Not Ready",
    "draft_message": "TO: candidate_1769021533@test.com\nCHANNEL: WhatsApp (+254700000000)\n\nHabari Juma! \ud83d\udc4b\n\nWe reviewed your application. You meet our minimum requirements for the Kibera region, but we noticed you might need support with business operations.\n\nWe would like to discuss how our training program can help bridge that gap.\n\n(Note: We saw you mentioned needing financing. We have banking partners who assist Curafa franchisees with working capital\u2014we can discuss this on the call.)\n\nAre you free next Tuesday for a 15-min intro call?",
    "next_step_due_date": "2026-01-28",
    "notes": null,
    "last_contact_date": null,
    "last_contact_channel": null
  },
  {
    "lead_id": "candidate_1769021595@test.com",
    "timestamp": "2026-01-21 21:53:15",
    "email": "candidate_1769021595@test.com",
    "first_name": "Sila",
    "middle_name": null,
    "last_name": "Paul",
    "phone": "254700000000",
    "source": "Web",
    "current_profession": "Clinical Officer",
    "experience_years": "3-4+ Years",
    "has_business_exp": "Yes",
    "certifications": null,
    "financial_readiness_input": "I have adequate resources (cash available)",
    "location_county_input": "London (Invalid)",
    "location_status_input": "No",
    "stage": "NO_FIT",
    "fit_score": 0.16,
    "fit_classification": "Not A Fit",
    "financial_readiness": "\ud83d\udfe2 Ready",
    "location_readiness": "\ud83d\udd34 Not Ready",
    "draft_message": "TO: candidate_1769021595@test.com\nCHANNEL: WhatsApp (+254700000000)\n\nDear Sila,\n\nThank you for applying to Access Afya. This year's process is competitive. Unfortunately, based on our territory and experience criteria, we cannot proceed with your application for London (Invalid) at this time.\n\nWe will keep your details for future opportunities.",
    "next_step_due_date": null,
    "notes": null,
    "last_contact_date": null,
    "last_contact_channel": null
  },
  {
    "lead_id": "candidate_1769021420@test.com",
    "timestamp": "2026-01-21 21:50:21",
    "email": "candidate_1769021420@test.com",
    "first_name": "John",
    "middle_name": null,
    "last_name": "Kamau",
    "phone": "254700000000",
    "source": "Web",
    "current_profession": "Clinical Officer",
    "experience_years": "3-4+ Years",
    "has_business_exp": "Yes",
    "certifications": null,
    "financial_readiness_input": "I have adequate resources (cash available)",
    "location_county_input": "Nairobi",
    "location_status_input": "No",
    "stage": "POTENTIAL_FIT",
    "fit_score": 0.2,
    "fit_classification": "Ideal Fit",
    "financial_readiness": "\ud83d\udfe2 Ready",
    "location_readiness": "\ud83d\udd34 Not Ready",
    "draft_message": "TO: candidate_1769021420@test.com\nCHANNEL: WhatsApp (+254700000000)\n\nHi John, just checking in! \n\nWe still have a slot open for an intro call this week. Please let us know if you are still interested?",
    "next_step_due_date": "2026-01-22",
    "notes": null,
    "last_contact_date": "2026-01-22 11:25:59",
    "last_contact_channel": "WhatsApp"
  },
  {
    "lead_id": "candidate_1769072247@test.com",
    "timestamp": "2026-01-22 11:57:27",
    "email": "candidate_1769072247@test.com",
    "first_name": "Sarah",
    "middle_name": null,
    "last_name": "Ali",
    "phone": "254700000000",
    "source": "Web",
    "current_profession": "Nurse",
    "experience_years": "3-4+ Years",
    "has_business_exp": "Yes",
    "certifications": null,
    "financial_readiness_input": "I have adequate resources (cash available)",
    "location_county_input": "Nairobi",
    "location_status_input": "No",
    "stage": "POTENTIAL_FIT",
    "fit_score": 0.19,
    "fit_classification": "Good Fit",
    "financial_readiness": "\ud83d\udfe2 Ready",
    "location_readiness": "\ud83d\udd34 Not Ready",
    "draft_message": "TO: candidate_1769072247@test.com\nCHANNEL: WhatsApp (+254700000000)\n\nHabari Sarah! \ud83d\udc4b\n\nWe think you could be a great fit for Curafa given your background as a Nurse.\n\nWe are expanding in Nairobi and would like to discuss next steps.\n\nAre you free next Tuesday for a 15-min intro call?",
    "next_step_due_date": "2026-01-29",
    "notes": null,
    "last_contact_date": null,
    "last_contact_channel": null
  },
  {
    "lead_id": "candidate_1769072270@test.com",
    "timestamp": "2026-01-22 11:57:50",
    "email": "candidate_1769072270@test.com",
    "first_name": "John",
    "middle_name": null,
    "last_name": "Peter",
    "phone": "254700000000",
    "source": "Web",
    "current_profession": "Nurse",
    "experience_years": "1-2 Years",
    "has_business_exp": "Yes",
    "certifications": null,
    "financial_readiness_input": "I have adequate resources (cash available)",
    "location_county_input": "Nairobi",
    "location_status_input": "No",
    "stage": "POTENTIAL_FIT",
    "fit_score": 0.17,
    "fit_classification": "Fair/Conditional Fit",
    "financial_readiness": "\ud83d\udfe2 Ready",
    "location_readiness": "\ud83d\udd34 Not Ready",
    "draft_message": "TO: candidate_1769072270@test.com\nCHANNEL: WhatsApp (+254700000000)\n\nHabari John! \ud83d\udc4b\n\nWe reviewed your application. You meet our minimum requirements for the Nairobi region, but we noticed you might need support with business operations.\n\nWe would like to discuss how our training program can help bridge that gap.\n\nAre you free next Tuesday for a 15-min intro call?",
    "next_step_due_date": "2026-01-29",
    "notes": null,
    "last_contact_date": null,
    "last_contact_channel": null
  }
]